{
  "uid": "an4-abhavagga",
  "root_name": "Ābhāvagga",
  "translated_name": "The Chapter on Brightness ",
  "node_type": "branch",
  "blurb": null,
  "acronym": null,
  "root_lang_iso": "pli",
  "root_lang_name": "Pāli",
  "child_range": "AN 4.141–150",
  "yellow_brick_road": true,
  "yellow_brick_road_count": 11,
  "children": [
    {
      "uid": "an4.141",
      "root_name": "Ābhāsutta",
      "translated_name": null,
      "acronym": "AN 4.141",
      "blurb": "The brightness of the moon, sun, fire, and wisdom.",
      "node_type": "leaf",
      "root_lang_iso": "pli",
      "root_lang_name": "Pāli",
      "child_range": null,
      "yellow_brick_road": true,
      "yellow_brick_road_count": 1
    },
    {
      "uid": "an4.142",
      "root_name": "Pabhāsutta",
      "translated_name": null,
      "acronym": "AN 4.142",
      "blurb": "The radiance of the moon, sun, fire, and wisdom.",
      "node_type": "leaf",
      "root_lang_iso": "pli",
      "root_lang_name": "Pāli",
      "child_range": null,
      "yellow_brick_road": true,
      "yellow_brick_road_count": 1
    },
    {
      "uid": "an4.143",
      "root_name": "Ālokasutta",
      "translated_name": null,
      "acronym": "AN 4.143",
      "blurb": "The lights of the moon, sun, fire, and wisdom.",
      "node_type": "leaf",
      "root_lang_iso": "pli",
      "root_lang_name": "Pāli",
      "child_range": null,
      "yellow_brick_road": true,
      "yellow_brick_road_count": 1
    },
    {
      "uid": "an4.144",
      "root_name": "Obhāsasutta",
      "translated_name": null,
      "acronym": "AN 4.144",
      "blurb": "The shining of the moon, sun, fire, and wisdom.",
      "node_type": "leaf",
      "root_lang_iso": "pli",
      "root_lang_name": "Pāli",
      "child_range": null,
      "yellow_brick_road": true,
      "yellow_brick_road_count": 2
    },
    {
      "uid": "an4.145",
      "root_name": "Pajjotasutta",
      "translated_name": null,
      "acronym": "AN 4.145",
      "blurb": "The lamps of the moon, sun, fire, and wisdom.",
      "node_type": "leaf",
      "root_lang_iso": "pli",
      "root_lang_name": "Pāli",
      "child_range": null,
      "yellow_brick_road": true,
      "yellow_brick_road_count": 1
    },
    {
      "uid": "an4.146",
      "root_name": "Paṭhamakālasutta",
      "translated_name": null,
      "acronym": "AN 4.146",
      "blurb": "A time for listening to the teaching, a time for discussing the teaching, a time for serenity, and a time for discernment.",
      "node_type": "leaf",
      "root_lang_iso": "pli",
      "root_lang_name": "Pāli",
      "child_range": null,
      "yellow_brick_road": true,
      "yellow_brick_road_count": 1
    },
    {
      "uid": "an4.147",
      "root_name": "Dutiyakālasutta",
      "translated_name": null,
      "acronym": "AN 4.147",
      "blurb": "A time for listening to the teaching, a time for discussing the teaching, a time for serenity, and a time for discernment.",
      "node_type": "leaf",
      "root_lang_iso": "pli",
      "root_lang_name": "Pāli",
      "child_range": null,
      "yellow_brick_road": true,
      "yellow_brick_road_count": 1
    },
    {
      "uid": "an4.148",
      "root_name": "Duccaritasutta",
      "translated_name": null,
      "acronym": "AN 4.148",
      "blurb": "Speech that’s lying, divisive, harsh, or meaningless.",
      "node_type": "leaf",
      "root_lang_iso": "pli",
      "root_lang_name": "Pāli",
      "child_range": null,
      "yellow_brick_road": true,
      "yellow_brick_road_count": 1
    },
    {
      "uid": "an4.149",
      "root_name": "Sucaritasutta",
      "translated_name": null,
      "acronym": "AN 4.149",
      "blurb": "Speech that’s true, harmonious, gentle, and meaningful.",
      "node_type": "leaf",
      "root_lang_iso": "pli",
      "root_lang_name": "Pāli",
      "child_range": null,
      "yellow_brick_road": true,
      "yellow_brick_road_count": 1
    },
    {
      "uid": "an4.150",
      "root_name": "Sārasutta",
      "translated_name": null,
      "acronym": "AN 4.150",
      "blurb": "Morality, convergence, wisdom, and freedom are essentials.",
      "node_type": "leaf",
      "root_lang_iso": "pli",
      "root_lang_name": "Pāli",
      "child_range": null,
      "yellow_brick_road": true,
      "yellow_brick_road_count": 1
    }
  ]
}