{
  "uid": "an5-aghatavagga",
  "root_name": "Āghātavagga",
  "translated_name": "The Chapter on Resentment ",
  "node_type": "branch",
  "blurb": null,
  "acronym": null,
  "root_lang_iso": "pli",
  "root_lang_name": "Pāli",
  "child_range": "AN 5.161–170",
  "yellow_brick_road": true,
  "yellow_brick_road_count": 14,
  "children": [
    {
      "uid": "an5.161",
      "root_name": "Paṭhamaāghātapaṭivinayasutta",
      "translated_name": null,
      "acronym": "AN 5.161",
      "blurb": "Five reflections to help eliminate resentment, in brief.",
      "node_type": "leaf",
      "root_lang_iso": "pli",
      "root_lang_name": "Pāli",
      "child_range": null,
      "yellow_brick_road": true,
      "yellow_brick_road_count": 2
    },
    {
      "uid": "an5.162",
      "root_name": "Dutiyaāghātapaṭivinayasutta",
      "translated_name": null,
      "acronym": "AN 5.162",
      "blurb": "Five reflections to help eliminate resentment, an explanation by Sāriputta..",
      "node_type": "leaf",
      "root_lang_iso": "pli",
      "root_lang_name": "Pāli",
      "child_range": null,
      "yellow_brick_road": true,
      "yellow_brick_road_count": 2
    },
    {
      "uid": "an5.163",
      "root_name": "Sākacchasutta",
      "translated_name": null,
      "acronym": "AN 5.163",
      "blurb": "Qualifications for a mendicant to hold a Dhamma discussion.",
      "node_type": "leaf",
      "root_lang_iso": "pli",
      "root_lang_name": "Pāli",
      "child_range": null,
      "yellow_brick_road": true,
      "yellow_brick_road_count": 1
    },
    {
      "uid": "an5.164",
      "root_name": "Sājīvasutta",
      "translated_name": null,
      "acronym": "AN 5.164",
      "blurb": "Qualifications for a mendicant to share their way of life.",
      "node_type": "leaf",
      "root_lang_iso": "pli",
      "root_lang_name": "Pāli",
      "child_range": null,
      "yellow_brick_road": true,
      "yellow_brick_road_count": 1
    },
    {
      "uid": "an5.165",
      "root_name": "Pañhapucchāsutta",
      "translated_name": null,
      "acronym": "AN 5.165",
      "blurb": "Sāriputta explains five reasons for asking a question, and the reason he asks a question.",
      "node_type": "leaf",
      "root_lang_iso": "pli",
      "root_lang_name": "Pāli",
      "child_range": null,
      "yellow_brick_road": true,
      "yellow_brick_road_count": 2
    },
    {
      "uid": "an5.166",
      "root_name": "Nirodhasutta",
      "translated_name": null,
      "acronym": "AN 5.166",
      "blurb": "Udāyī refuses to believe Sāriputta’s description of the achievements of an accomplished meditator. The Buddha dismisses Udāyī’s foolishness, and outlines the reasons senior mendicants should be respected. ",
      "node_type": "leaf",
      "root_lang_iso": "pli",
      "root_lang_name": "Pāli",
      "child_range": null,
      "yellow_brick_road": true,
      "yellow_brick_road_count": 1
    },
    {
      "uid": "an5.167",
      "root_name": "Codanāsutta",
      "translated_name": null,
      "acronym": "AN 5.167",
      "blurb": "Factors that a mendicant should establish in themselves before accusing another.",
      "node_type": "leaf",
      "root_lang_iso": "pli",
      "root_lang_name": "Pāli",
      "child_range": null,
      "yellow_brick_road": true,
      "yellow_brick_road_count": 2
    },
    {
      "uid": "an5.168",
      "root_name": "Sīlasutta",
      "translated_name": null,
      "acronym": "AN 5.168",
      "blurb": "Lack of ethics prevents the attaining of samādhi, wisdom, and freedom.",
      "node_type": "leaf",
      "root_lang_iso": "pli",
      "root_lang_name": "Pāli",
      "child_range": null,
      "yellow_brick_road": true,
      "yellow_brick_road_count": 1
    },
    {
      "uid": "an5.169",
      "root_name": "Khippanisantisutta",
      "translated_name": null,
      "acronym": "AN 5.169",
      "blurb": "Ānanda asks Sāriputta to explain what it means to be quick-witted, but Sāriputta gets Ānanda to explain it himself.",
      "node_type": "leaf",
      "root_lang_iso": "pli",
      "root_lang_name": "Pāli",
      "child_range": null,
      "yellow_brick_road": true,
      "yellow_brick_road_count": 1
    },
    {
      "uid": "an5.170",
      "root_name": "Bhaddajisutta",
      "translated_name": null,
      "acronym": "AN 5.170",
      "blurb": "Ānanda asks Bhaddaji about the best sense objects, and corrects his answer.",
      "node_type": "leaf",
      "root_lang_iso": "pli",
      "root_lang_name": "Pāli",
      "child_range": null,
      "yellow_brick_road": true,
      "yellow_brick_road_count": 1
    }
  ]
}