{
  "uid": "ea42",
  "root_name": "Ekottarikāgama 42",
  "translated_name": null,
  "node_type": "branch",
  "blurb": null,
  "acronym": null,
  "root_lang_iso": "lzh",
  "root_lang_name": "Chinese",
  "child_range": null,
  "yellow_brick_road": false,
  "yellow_brick_road_count": 0,
  "children": [
    {
      "uid": "ea42.1",
      "root_name": "非時",
      "translated_name": null,
      "acronym": "EA 42.1",
      "blurb": null,
      "node_type": "leaf",
      "root_lang_iso": "lzh",
      "root_lang_name": "Chinese",
      "child_range": null,
      "yellow_brick_road": false,
      "yellow_brick_road_count": 0
    },
    {
      "uid": "ea42.2",
      "root_name": "泥黎",
      "translated_name": null,
      "acronym": "EA 42.2",
      "blurb": null,
      "node_type": "leaf",
      "root_lang_iso": "lzh",
      "root_lang_name": "Chinese",
      "child_range": null,
      "yellow_brick_road": false,
      "yellow_brick_road_count": 0
    },
    {
      "uid": "ea42.3",
      "root_name": "道",
      "translated_name": null,
      "acronym": "EA 42.3",
      "blurb": null,
      "node_type": "leaf",
      "root_lang_iso": "lzh",
      "root_lang_name": "Chinese",
      "child_range": null,
      "yellow_brick_road": false,
      "yellow_brick_road_count": 0
    },
    {
      "uid": "ea42.4",
      "root_name": "須倫",
      "translated_name": null,
      "acronym": "EA 42.4",
      "blurb": null,
      "node_type": "leaf",
      "root_lang_iso": "lzh",
      "root_lang_name": "Chinese",
      "child_range": null,
      "yellow_brick_road": false,
      "yellow_brick_road_count": 0
    },
    {
      "uid": "ea42.5",
      "root_name": "地動",
      "translated_name": null,
      "acronym": "EA 42.5",
      "blurb": null,
      "node_type": "leaf",
      "root_lang_iso": "lzh",
      "root_lang_name": "Chinese",
      "child_range": null,
      "yellow_brick_road": false,
      "yellow_brick_road_count": 0
    },
    {
      "uid": "ea42.6",
      "root_name": "大人八念",
      "translated_name": null,
      "acronym": "EA 42.6",
      "blurb": null,
      "node_type": "leaf",
      "root_lang_iso": "lzh",
      "root_lang_name": "Chinese",
      "child_range": null,
      "yellow_brick_road": false,
      "yellow_brick_road_count": 0
    },
    {
      "uid": "ea42.7",
      "root_name": "眾",
      "translated_name": null,
      "acronym": "EA 42.7",
      "blurb": null,
      "node_type": "leaf",
      "root_lang_iso": "lzh",
      "root_lang_name": "Chinese",
      "child_range": null,
      "yellow_brick_road": false,
      "yellow_brick_road_count": 0
    },
    {
      "uid": "ea42.8",
      "root_name": "",
      "translated_name": null,
      "acronym": "EA 42.8",
      "blurb": null,
      "node_type": "leaf",
      "root_lang_iso": "lzh",
      "root_lang_name": "Chinese",
      "child_range": null,
      "yellow_brick_road": false,
      "yellow_brick_road_count": 0
    },
    {
      "uid": "ea42.9",
      "root_name": "善男子施",
      "translated_name": null,
      "acronym": "EA 42.9",
      "blurb": null,
      "node_type": "leaf",
      "root_lang_iso": "lzh",
      "root_lang_name": "Chinese",
      "child_range": null,
      "yellow_brick_road": false,
      "yellow_brick_road_count": 0
    },
    {
      "uid": "ea42.10",
      "root_name": "道",
      "translated_name": null,
      "acronym": "EA 42.10",
      "blurb": null,
      "node_type": "leaf",
      "root_lang_iso": "lzh",
      "root_lang_name": "Chinese",
      "child_range": null,
      "yellow_brick_road": false,
      "yellow_brick_road_count": 0
    }
  ]
}