{
  "uid": "ma-ot",
  "root_name": "Other Madhyama Sūtras",
  "translated_name": "Other Middle Discourses ",
  "node_type": "branch",
  "blurb": "72 middle-length discourses that in the Taishō edition of the Chinese canon have been gathered in the first volume, at sūtra numbers 27–98, following the Madhyamāgama. These are miscellaneous translations of various discourses from the Majjhima, made at various times by various translators.",
  "acronym": "Other MA",
  "root_lang_iso": "lzh",
  "root_lang_name": "Chinese",
  "child_range": "MA ot",
  "yellow_brick_road": false,
  "yellow_brick_road_count": 0,
  "children": [
    {
      "uid": "t27",
      "root_name": "七知",
      "translated_name": null,
      "acronym": "T 27",
      "blurb": null,
      "node_type": "leaf",
      "root_lang_iso": "lzh",
      "root_lang_name": "Chinese",
      "child_range": null,
      "yellow_brick_road": false,
      "yellow_brick_road_count": 0
    },
    {
      "uid": "t28",
      "root_name": "園生樹",
      "translated_name": null,
      "acronym": "T 28",
      "blurb": null,
      "node_type": "leaf",
      "root_lang_iso": "lzh",
      "root_lang_name": "Chinese",
      "child_range": null,
      "yellow_brick_road": false,
      "yellow_brick_road_count": 0
    },
    {
      "uid": "t29",
      "root_name": "鹹水喻",
      "translated_name": null,
      "acronym": "T 29",
      "blurb": null,
      "node_type": "leaf",
      "root_lang_iso": "lzh",
      "root_lang_name": "Chinese",
      "child_range": null,
      "yellow_brick_road": false,
      "yellow_brick_road_count": 0
    },
    {
      "uid": "t30",
      "root_name": "薩缽多酥哩踰捺野",
      "translated_name": null,
      "acronym": "T 30",
      "blurb": null,
      "node_type": "leaf",
      "root_lang_iso": "lzh",
      "root_lang_name": "Chinese",
      "child_range": null,
      "yellow_brick_road": false,
      "yellow_brick_road_count": 0
    },
    {
      "uid": "t31",
      "root_name": "一切流攝守因",
      "translated_name": null,
      "acronym": "T 31",
      "blurb": null,
      "node_type": "leaf",
      "root_lang_iso": "lzh",
      "root_lang_name": "Chinese",
      "child_range": null,
      "yellow_brick_road": false,
      "yellow_brick_road_count": 0
    },
    {
      "uid": "t32",
      "root_name": "四諦",
      "translated_name": null,
      "acronym": "T 32",
      "blurb": null,
      "node_type": "leaf",
      "root_lang_iso": "lzh",
      "root_lang_name": "Chinese",
      "child_range": null,
      "yellow_brick_road": false,
      "yellow_brick_road_count": 0
    },
    {
      "uid": "t33",
      "root_name": "恒水",
      "translated_name": null,
      "acronym": "T 33",
      "blurb": null,
      "node_type": "leaf",
      "root_lang_iso": "lzh",
      "root_lang_name": "Chinese",
      "child_range": null,
      "yellow_brick_road": false,
      "yellow_brick_road_count": 0
    },
    {
      "uid": "t34",
      "root_name": "法海",
      "translated_name": null,
      "acronym": "T 34",
      "blurb": null,
      "node_type": "leaf",
      "root_lang_iso": "lzh",
      "root_lang_name": "Chinese",
      "child_range": null,
      "yellow_brick_road": false,
      "yellow_brick_road_count": 0
    },
    {
      "uid": "t35",
      "root_name": "海八德",
      "translated_name": null,
      "acronym": "T 35",
      "blurb": null,
      "node_type": "leaf",
      "root_lang_iso": "lzh",
      "root_lang_name": "Chinese",
      "child_range": null,
      "yellow_brick_road": false,
      "yellow_brick_road_count": 0
    },
    {
      "uid": "t36",
      "root_name": "本相猗致",
      "translated_name": null,
      "acronym": "T 36",
      "blurb": null,
      "node_type": "leaf",
      "root_lang_iso": "lzh",
      "root_lang_name": "Chinese",
      "child_range": null,
      "yellow_brick_road": false,
      "yellow_brick_road_count": 0
    },
    {
      "uid": "t37",
      "root_name": "緣本致",
      "translated_name": null,
      "acronym": "T 37",
      "blurb": null,
      "node_type": "leaf",
      "root_lang_iso": "lzh",
      "root_lang_name": "Chinese",
      "child_range": null,
      "yellow_brick_road": false,
      "yellow_brick_road_count": 0
    },
    {
      "uid": "t38",
      "root_name": "輪王七寶",
      "translated_name": null,
      "acronym": "T 38",
      "blurb": null,
      "node_type": "leaf",
      "root_lang_iso": "lzh",
      "root_lang_name": "Chinese",
      "child_range": null,
      "yellow_brick_road": false,
      "yellow_brick_road_count": 0
    },
    {
      "uid": "t39",
      "root_name": "頂生王故事",
      "translated_name": null,
      "acronym": "T 39",
      "blurb": null,
      "node_type": "leaf",
      "root_lang_iso": "lzh",
      "root_lang_name": "Chinese",
      "child_range": null,
      "yellow_brick_road": false,
      "yellow_brick_road_count": 0
    },
    {
      "uid": "t40",
      "root_name": "文陀竭王",
      "translated_name": null,
      "acronym": "T 40",
      "blurb": null,
      "node_type": "leaf",
      "root_lang_iso": "lzh",
      "root_lang_name": "Chinese",
      "child_range": null,
      "yellow_brick_road": false,
      "yellow_brick_road_count": 0
    },
    {
      "uid": "t41",
      "root_name": "頻婆娑羅王",
      "translated_name": null,
      "acronym": "T 41",
      "blurb": null,
      "node_type": "leaf",
      "root_lang_iso": "lzh",
      "root_lang_name": "Chinese",
      "child_range": null,
      "yellow_brick_road": false,
      "yellow_brick_road_count": 0
    },
    {
      "uid": "t42",
      "root_name": "鐵城泥犁",
      "translated_name": null,
      "acronym": "T 42",
      "blurb": null,
      "node_type": "leaf",
      "root_lang_iso": "lzh",
      "root_lang_name": "Chinese",
      "child_range": null,
      "yellow_brick_road": false,
      "yellow_brick_road_count": 0
    },
    {
      "uid": "t43",
      "root_name": "閻羅王五天使者",
      "translated_name": null,
      "acronym": "T 43",
      "blurb": null,
      "node_type": "leaf",
      "root_lang_iso": "lzh",
      "root_lang_name": "Chinese",
      "child_range": null,
      "yellow_brick_road": false,
      "yellow_brick_road_count": 0
    },
    {
      "uid": "t44",
      "root_name": "古來世時",
      "translated_name": null,
      "acronym": "T 44",
      "blurb": null,
      "node_type": "leaf",
      "root_lang_iso": "lzh",
      "root_lang_name": "Chinese",
      "child_range": null,
      "yellow_brick_road": false,
      "yellow_brick_road_count": 0
    },
    {
      "uid": "t45",
      "root_name": "大正句王",
      "translated_name": null,
      "acronym": "T 45",
      "blurb": null,
      "node_type": "leaf",
      "root_lang_iso": "lzh",
      "root_lang_name": "Chinese",
      "child_range": null,
      "yellow_brick_road": false,
      "yellow_brick_road_count": 0
    },
    {
      "uid": "t46",
      "root_name": "阿那律八念",
      "translated_name": null,
      "acronym": "T 46",
      "blurb": null,
      "node_type": "leaf",
      "root_lang_iso": "lzh",
      "root_lang_name": "Chinese",
      "child_range": null,
      "yellow_brick_road": false,
      "yellow_brick_road_count": 0
    },
    {
      "uid": "t47",
      "root_name": "離睡",
      "translated_name": null,
      "acronym": "T 47",
      "blurb": null,
      "node_type": "leaf",
      "root_lang_iso": "lzh",
      "root_lang_name": "Chinese",
      "child_range": null,
      "yellow_brick_road": false,
      "yellow_brick_road_count": 0
    },
    {
      "uid": "t48",
      "root_name": "是法非法",
      "translated_name": null,
      "acronym": "T 48",
      "blurb": null,
      "node_type": "leaf",
      "root_lang_iso": "lzh",
      "root_lang_name": "Chinese",
      "child_range": null,
      "yellow_brick_road": false,
      "yellow_brick_road_count": 0
    },
    {
      "uid": "t49",
      "root_name": "求欲",
      "translated_name": null,
      "acronym": "T 49",
      "blurb": null,
      "node_type": "leaf",
      "root_lang_iso": "lzh",
      "root_lang_name": "Chinese",
      "child_range": null,
      "yellow_brick_road": false,
      "yellow_brick_road_count": 0
    },
    {
      "uid": "t50",
      "root_name": "受歲",
      "translated_name": null,
      "acronym": "T 50",
      "blurb": null,
      "node_type": "leaf",
      "root_lang_iso": "lzh",
      "root_lang_name": "Chinese",
      "child_range": null,
      "yellow_brick_road": false,
      "yellow_brick_road_count": 0
    },
    {
      "uid": "t51",
      "root_name": "梵志計水淨",
      "translated_name": null,
      "acronym": "T 51",
      "blurb": null,
      "node_type": "leaf",
      "root_lang_iso": "lzh",
      "root_lang_name": "Chinese",
      "child_range": null,
      "yellow_brick_road": false,
      "yellow_brick_road_count": 0
    },
    {
      "uid": "t52",
      "root_name": "大生義",
      "translated_name": null,
      "acronym": "T 52",
      "blurb": null,
      "node_type": "leaf",
      "root_lang_iso": "lzh",
      "root_lang_name": "Chinese",
      "child_range": null,
      "yellow_brick_road": false,
      "yellow_brick_road_count": 0
    },
    {
      "uid": "t53",
      "root_name": "苦陰",
      "translated_name": null,
      "acronym": "T 53",
      "blurb": null,
      "node_type": "leaf",
      "root_lang_iso": "lzh",
      "root_lang_name": "Chinese",
      "child_range": null,
      "yellow_brick_road": false,
      "yellow_brick_road_count": 0
    },
    {
      "uid": "t54",
      "root_name": "釋摩男本四子",
      "translated_name": null,
      "acronym": "T 54",
      "blurb": null,
      "node_type": "leaf",
      "root_lang_iso": "lzh",
      "root_lang_name": "Chinese",
      "child_range": null,
      "yellow_brick_road": false,
      "yellow_brick_road_count": 0
    },
    {
      "uid": "t55",
      "root_name": "苦陰因事",
      "translated_name": null,
      "acronym": "T 55",
      "blurb": null,
      "node_type": "leaf",
      "root_lang_iso": "lzh",
      "root_lang_name": "Chinese",
      "child_range": null,
      "yellow_brick_road": false,
      "yellow_brick_road_count": 0
    },
    {
      "uid": "t56",
      "root_name": "樂想",
      "translated_name": null,
      "acronym": "T 56",
      "blurb": null,
      "node_type": "leaf",
      "root_lang_iso": "lzh",
      "root_lang_name": "Chinese",
      "child_range": null,
      "yellow_brick_road": false,
      "yellow_brick_road_count": 0
    },
    {
      "uid": "t57",
      "root_name": "漏分布",
      "translated_name": null,
      "acronym": "T 57",
      "blurb": null,
      "node_type": "leaf",
      "root_lang_iso": "lzh",
      "root_lang_name": "Chinese",
      "child_range": null,
      "yellow_brick_road": false,
      "yellow_brick_road_count": 0
    },
    {
      "uid": "t58",
      "root_name": "阿耨風",
      "translated_name": null,
      "acronym": "T 58",
      "blurb": null,
      "node_type": "leaf",
      "root_lang_iso": "lzh",
      "root_lang_name": "Chinese",
      "child_range": null,
      "yellow_brick_road": false,
      "yellow_brick_road_count": 0
    },
    {
      "uid": "t59",
      "root_name": "諸法本",
      "translated_name": null,
      "acronym": "T 59",
      "blurb": null,
      "node_type": "leaf",
      "root_lang_iso": "lzh",
      "root_lang_name": "Chinese",
      "child_range": null,
      "yellow_brick_road": false,
      "yellow_brick_road_count": 0
    },
    {
      "uid": "t60",
      "root_name": "瞿曇彌記果",
      "translated_name": null,
      "acronym": "T 60",
      "blurb": null,
      "node_type": "leaf",
      "root_lang_iso": "lzh",
      "root_lang_name": "Chinese",
      "child_range": null,
      "yellow_brick_road": false,
      "yellow_brick_road_count": 0
    },
    {
      "uid": "t61",
      "root_name": "受新歲",
      "translated_name": null,
      "acronym": "T 61",
      "blurb": null,
      "node_type": "leaf",
      "root_lang_iso": "lzh",
      "root_lang_name": "Chinese",
      "child_range": null,
      "yellow_brick_road": false,
      "yellow_brick_road_count": 0
    },
    {
      "uid": "t62",
      "root_name": "新歲",
      "translated_name": null,
      "acronym": "T 62",
      "blurb": null,
      "node_type": "leaf",
      "root_lang_iso": "lzh",
      "root_lang_name": "Chinese",
      "child_range": null,
      "yellow_brick_road": false,
      "yellow_brick_road_count": 0
    },
    {
      "uid": "t63",
      "root_name": "解夏",
      "translated_name": null,
      "acronym": "T 63",
      "blurb": null,
      "node_type": "leaf",
      "root_lang_iso": "lzh",
      "root_lang_name": "Chinese",
      "child_range": null,
      "yellow_brick_road": false,
      "yellow_brick_road_count": 0
    },
    {
      "uid": "t64",
      "root_name": "瞻婆比丘",
      "translated_name": null,
      "acronym": "T 64",
      "blurb": null,
      "node_type": "leaf",
      "root_lang_iso": "lzh",
      "root_lang_name": "Chinese",
      "child_range": null,
      "yellow_brick_road": false,
      "yellow_brick_road_count": 0
    },
    {
      "uid": "t65",
      "root_name": "伏淫",
      "translated_name": null,
      "acronym": "T 65",
      "blurb": null,
      "node_type": "leaf",
      "root_lang_iso": "lzh",
      "root_lang_name": "Chinese",
      "child_range": null,
      "yellow_brick_road": false,
      "yellow_brick_road_count": 0
    },
    {
      "uid": "t66",
      "root_name": "魔嬈亂",
      "translated_name": null,
      "acronym": "T 66",
      "blurb": null,
      "node_type": "leaf",
      "root_lang_iso": "lzh",
      "root_lang_name": "Chinese",
      "child_range": null,
      "yellow_brick_road": false,
      "yellow_brick_road_count": 0
    },
    {
      "uid": "t67",
      "root_name": "弊魔試目連",
      "translated_name": null,
      "acronym": "T 67",
      "blurb": null,
      "node_type": "leaf",
      "root_lang_iso": "lzh",
      "root_lang_name": "Chinese",
      "child_range": null,
      "yellow_brick_road": false,
      "yellow_brick_road_count": 0
    },
    {
      "uid": "t68",
      "root_name": "賴吒和羅",
      "translated_name": null,
      "acronym": "T 68",
      "blurb": null,
      "node_type": "leaf",
      "root_lang_iso": "lzh",
      "root_lang_name": "Chinese",
      "child_range": null,
      "yellow_brick_road": false,
      "yellow_brick_road_count": 0
    },
    {
      "uid": "t69",
      "root_name": "護國",
      "translated_name": null,
      "acronym": "T 69",
      "blurb": null,
      "node_type": "leaf",
      "root_lang_iso": "lzh",
      "root_lang_name": "Chinese",
      "child_range": null,
      "yellow_brick_road": false,
      "yellow_brick_road_count": 0
    },
    {
      "uid": "t70",
      "root_name": "數",
      "translated_name": null,
      "acronym": "T 70",
      "blurb": null,
      "node_type": "leaf",
      "root_lang_iso": "lzh",
      "root_lang_name": "Chinese",
      "child_range": null,
      "yellow_brick_road": false,
      "yellow_brick_road_count": 0
    },
    {
      "uid": "t71",
      "root_name": "梵志頞波羅延問種尊",
      "translated_name": null,
      "acronym": "T 71",
      "blurb": null,
      "node_type": "leaf",
      "root_lang_iso": "lzh",
      "root_lang_name": "Chinese",
      "child_range": null,
      "yellow_brick_road": false,
      "yellow_brick_road_count": 0
    },
    {
      "uid": "t72",
      "root_name": "三歸五戒慈心厭離功德",
      "translated_name": null,
      "acronym": "T 72",
      "blurb": null,
      "node_type": "leaf",
      "root_lang_iso": "lzh",
      "root_lang_name": "Chinese",
      "child_range": null,
      "yellow_brick_road": false,
      "yellow_brick_road_count": 0
    },
    {
      "uid": "t73",
      "root_name": "須達",
      "translated_name": null,
      "acronym": "T 73",
      "blurb": null,
      "node_type": "leaf",
      "root_lang_iso": "lzh",
      "root_lang_name": "Chinese",
      "child_range": null,
      "yellow_brick_road": false,
      "yellow_brick_road_count": 0
    },
    {
      "uid": "t74",
      "root_name": "長者施報",
      "translated_name": null,
      "acronym": "T 74",
      "blurb": null,
      "node_type": "leaf",
      "root_lang_iso": "lzh",
      "root_lang_name": "Chinese",
      "child_range": null,
      "yellow_brick_road": false,
      "yellow_brick_road_count": 0
    },
    {
      "uid": "t75",
      "root_name": "佛為黃竹園老婆羅門說學",
      "translated_name": null,
      "acronym": "T 75",
      "blurb": null,
      "node_type": "leaf",
      "root_lang_iso": "lzh",
      "root_lang_name": "Chinese",
      "child_range": null,
      "yellow_brick_road": false,
      "yellow_brick_road_count": 0
    },
    {
      "uid": "t76",
      "root_name": "梵摩渝",
      "translated_name": null,
      "acronym": "T 76",
      "blurb": null,
      "node_type": "leaf",
      "root_lang_iso": "lzh",
      "root_lang_name": "Chinese",
      "child_range": null,
      "yellow_brick_road": false,
      "yellow_brick_road_count": 0
    },
    {
      "uid": "t77",
      "root_name": "尊上",
      "translated_name": null,
      "acronym": "T 77",
      "blurb": null,
      "node_type": "leaf",
      "root_lang_iso": "lzh",
      "root_lang_name": "Chinese",
      "child_range": null,
      "yellow_brick_road": false,
      "yellow_brick_road_count": 0
    },
    {
      "uid": "t78",
      "root_name": "兜調",
      "translated_name": null,
      "acronym": "T 78",
      "blurb": null,
      "node_type": "leaf",
      "root_lang_iso": "lzh",
      "root_lang_name": "Chinese",
      "child_range": null,
      "yellow_brick_road": false,
      "yellow_brick_road_count": 0
    },
    {
      "uid": "t79",
      "root_name": "鸚鵡",
      "translated_name": null,
      "acronym": "T 79",
      "blurb": null,
      "node_type": "leaf",
      "root_lang_iso": "lzh",
      "root_lang_name": "Chinese",
      "child_range": null,
      "yellow_brick_road": false,
      "yellow_brick_road_count": 0
    },
    {
      "uid": "t80",
      "root_name": "佛為首迦長者說業報差別",
      "translated_name": null,
      "acronym": "T 80",
      "blurb": null,
      "node_type": "leaf",
      "root_lang_iso": "lzh",
      "root_lang_name": "Chinese",
      "child_range": null,
      "yellow_brick_road": false,
      "yellow_brick_road_count": 0
    },
    {
      "uid": "t81",
      "root_name": "分別善惡報應",
      "translated_name": null,
      "acronym": "T 81",
      "blurb": null,
      "node_type": "leaf",
      "root_lang_iso": "lzh",
      "root_lang_name": "Chinese",
      "child_range": null,
      "yellow_brick_road": false,
      "yellow_brick_road_count": 0
    },
    {
      "uid": "t82",
      "root_name": "意",
      "translated_name": null,
      "acronym": "T 82",
      "blurb": null,
      "node_type": "leaf",
      "root_lang_iso": "lzh",
      "root_lang_name": "Chinese",
      "child_range": null,
      "yellow_brick_road": false,
      "yellow_brick_road_count": 0
    },
    {
      "uid": "t83",
      "root_name": "應法",
      "translated_name": null,
      "acronym": "T 83",
      "blurb": null,
      "node_type": "leaf",
      "root_lang_iso": "lzh",
      "root_lang_name": "Chinese",
      "child_range": null,
      "yellow_brick_road": false,
      "yellow_brick_road_count": 0
    },
    {
      "uid": "t84",
      "root_name": "分別布施",
      "translated_name": null,
      "acronym": "T 84",
      "blurb": null,
      "node_type": "leaf",
      "root_lang_iso": "lzh",
      "root_lang_name": "Chinese",
      "child_range": null,
      "yellow_brick_road": false,
      "yellow_brick_road_count": 0
    },
    {
      "uid": "t85",
      "root_name": "息諍因緣",
      "translated_name": null,
      "acronym": "T 85",
      "blurb": null,
      "node_type": "leaf",
      "root_lang_iso": "lzh",
      "root_lang_name": "Chinese",
      "child_range": null,
      "yellow_brick_road": false,
      "yellow_brick_road_count": 0
    },
    {
      "uid": "t86",
      "root_name": "泥犁",
      "translated_name": null,
      "acronym": "T 86",
      "blurb": null,
      "node_type": "leaf",
      "root_lang_iso": "lzh",
      "root_lang_name": "Chinese",
      "child_range": null,
      "yellow_brick_road": false,
      "yellow_brick_road_count": 0
    },
    {
      "uid": "t87",
      "root_name": "齋",
      "translated_name": null,
      "acronym": "T 87",
      "blurb": null,
      "node_type": "leaf",
      "root_lang_iso": "lzh",
      "root_lang_name": "Chinese",
      "child_range": null,
      "yellow_brick_road": false,
      "yellow_brick_road_count": 0
    },
    {
      "uid": "t88",
      "root_name": "優陂夷墮舍迦",
      "translated_name": null,
      "acronym": "T 88",
      "blurb": null,
      "node_type": "leaf",
      "root_lang_iso": "lzh",
      "root_lang_name": "Chinese",
      "child_range": null,
      "yellow_brick_road": false,
      "yellow_brick_road_count": 0
    },
    {
      "uid": "t89",
      "root_name": "八關齋",
      "translated_name": null,
      "acronym": "T 89",
      "blurb": null,
      "node_type": "leaf",
      "root_lang_iso": "lzh",
      "root_lang_name": "Chinese",
      "child_range": null,
      "yellow_brick_road": false,
      "yellow_brick_road_count": 0
    },
    {
      "uid": "t90",
      "root_name": "鞞摩肅",
      "translated_name": null,
      "acronym": "T 90",
      "blurb": null,
      "node_type": "leaf",
      "root_lang_iso": "lzh",
      "root_lang_name": "Chinese",
      "child_range": null,
      "yellow_brick_road": false,
      "yellow_brick_road_count": 0
    },
    {
      "uid": "t91",
      "root_name": "婆羅門子命終愛念不離",
      "translated_name": null,
      "acronym": "T 91",
      "blurb": null,
      "node_type": "leaf",
      "root_lang_iso": "lzh",
      "root_lang_name": "Chinese",
      "child_range": null,
      "yellow_brick_road": false,
      "yellow_brick_road_count": 0
    },
    {
      "uid": "t92",
      "root_name": "十支居士八城人",
      "translated_name": null,
      "acronym": "T 92",
      "blurb": null,
      "node_type": "leaf",
      "root_lang_iso": "lzh",
      "root_lang_name": "Chinese",
      "child_range": null,
      "yellow_brick_road": false,
      "yellow_brick_road_count": 0
    },
    {
      "uid": "t93",
      "root_name": "邪見",
      "translated_name": null,
      "acronym": "T 93",
      "blurb": null,
      "node_type": "leaf",
      "root_lang_iso": "lzh",
      "root_lang_name": "Chinese",
      "child_range": null,
      "yellow_brick_road": false,
      "yellow_brick_road_count": 0
    },
    {
      "uid": "t94",
      "root_name": "箭喻",
      "translated_name": null,
      "acronym": "T 94",
      "blurb": null,
      "node_type": "leaf",
      "root_lang_iso": "lzh",
      "root_lang_name": "Chinese",
      "child_range": null,
      "yellow_brick_road": false,
      "yellow_brick_road_count": 0
    },
    {
      "uid": "t95",
      "root_name": "蟻喻",
      "translated_name": null,
      "acronym": "T 95",
      "blurb": null,
      "node_type": "leaf",
      "root_lang_iso": "lzh",
      "root_lang_name": "Chinese",
      "child_range": null,
      "yellow_brick_road": false,
      "yellow_brick_road_count": 0
    },
    {
      "uid": "t96",
      "root_name": "治意",
      "translated_name": null,
      "acronym": "T 96",
      "blurb": null,
      "node_type": "leaf",
      "root_lang_iso": "lzh",
      "root_lang_name": "Chinese",
      "child_range": null,
      "yellow_brick_road": false,
      "yellow_brick_road_count": 0
    },
    {
      "uid": "t97",
      "root_name": "廣義法門",
      "translated_name": null,
      "acronym": "T 97",
      "blurb": null,
      "node_type": "leaf",
      "root_lang_iso": "lzh",
      "root_lang_name": "Chinese",
      "child_range": null,
      "yellow_brick_road": false,
      "yellow_brick_road_count": 0
    },
    {
      "uid": "t98",
      "root_name": "普法義",
      "translated_name": null,
      "acronym": "T 98",
      "blurb": null,
      "node_type": "leaf",
      "root_lang_iso": "lzh",
      "root_lang_name": "Chinese",
      "child_range": null,
      "yellow_brick_road": false,
      "yellow_brick_road_count": 0
    }
  ]
}