{
  "uid": "sn11-tatiyavagga",
  "root_name": "Tatiyavagga",
  "translated_name": "Chapter Three ",
  "node_type": "branch",
  "blurb": null,
  "acronym": null,
  "root_lang_iso": "pli",
  "root_lang_name": "Pāli",
  "child_range": "SN 11.21–25",
  "yellow_brick_road": true,
  "yellow_brick_road_count": 13,
  "children": [
    {
      "uid": "sn11.21",
      "root_name": "Chetvāsutta",
      "translated_name": null,
      "acronym": "SN 11.21",
      "blurb": "Anger is the only thing whose slaying the Buddha commends.",
      "node_type": "leaf",
      "root_lang_iso": "pli",
      "root_lang_name": "Pāli",
      "child_range": null,
      "yellow_brick_road": true,
      "yellow_brick_road_count": 2
    },
    {
      "uid": "sn11.22",
      "root_name": "Dubbaṇṇiyasutta",
      "translated_name": null,
      "acronym": "SN 11.22",
      "blurb": "When an ugly spirit takes Sakka’s throne, the gods were outraged. But the more they complained, the prettier he became. Sakka realized this was the so-called “anger eating spirit”, and treated him with kindness and respect. ",
      "node_type": "leaf",
      "root_lang_iso": "pli",
      "root_lang_name": "Pāli",
      "child_range": null,
      "yellow_brick_road": true,
      "yellow_brick_road_count": 3
    },
    {
      "uid": "sn11.23",
      "root_name": "Sambarimāyāsutta",
      "translated_name": null,
      "acronym": "SN 11.23",
      "blurb": "When Vepacitti fell ill, Sakka visited his old adversary, who begged to be cured. But Sakka demanded to be taught a powerful magic spell first.",
      "node_type": "leaf",
      "root_lang_iso": "pli",
      "root_lang_name": "Pāli",
      "child_range": null,
      "yellow_brick_road": true,
      "yellow_brick_road_count": 3
    },
    {
      "uid": "sn11.24",
      "root_name": "Accayasutta",
      "translated_name": null,
      "acronym": "SN 11.24",
      "blurb": "When two mendicants have a falling out, the Buddha recalls the wise words of Sakka on not letting anger ruin friendship.",
      "node_type": "leaf",
      "root_lang_iso": "pli",
      "root_lang_name": "Pāli",
      "child_range": null,
      "yellow_brick_road": true,
      "yellow_brick_road_count": 3
    },
    {
      "uid": "sn11.25",
      "root_name": "Akkodhasutta",
      "translated_name": null,
      "acronym": "SN 11.25",
      "blurb": "The Buddha recalls the words of Sakka warning of how anger crushes people like an avalanche",
      "node_type": "leaf",
      "root_lang_iso": "pli",
      "root_lang_name": "Pāli",
      "child_range": null,
      "yellow_brick_road": true,
      "yellow_brick_road_count": 2
    }
  ]
}