{
  "uid": "sn45-dutiyagangapeyyalavagga",
  "root_name": "Dutiyagaṅgāpeyyālavagga",
  "translated_name": "The Chapter of Abbreviated Texts on the Ganges ",
  "node_type": "branch",
  "blurb": null,
  "acronym": null,
  "root_lang_iso": "pli",
  "root_lang_name": "Pāli",
  "child_range": "SN 45.103–138",
  "yellow_brick_road": true,
  "yellow_brick_road_count": 15,
  "children": [
    {
      "uid": "sn45.103",
      "root_name": "Paṭhamapācīnaninnasutta",
      "translated_name": null,
      "acronym": "SN 45.103",
      "blurb": null,
      "node_type": "leaf",
      "root_lang_iso": "pli",
      "root_lang_name": "Pāli",
      "child_range": null,
      "yellow_brick_road": true,
      "yellow_brick_road_count": 2
    },
    {
      "uid": "sn45.104-108",
      "root_name": "Dutiyādipācīnaninnasuttapañcaka",
      "translated_name": null,
      "acronym": "SN 45.104–108",
      "blurb": null,
      "node_type": "leaf",
      "root_lang_iso": "pli",
      "root_lang_name": "Pāli",
      "child_range": null,
      "yellow_brick_road": true,
      "yellow_brick_road_count": 1
    },
    {
      "uid": "sn45.109",
      "root_name": "Paṭhamasamuddaninnasutta",
      "translated_name": null,
      "acronym": "SN 45.109",
      "blurb": null,
      "node_type": "leaf",
      "root_lang_iso": "pli",
      "root_lang_name": "Pāli",
      "child_range": null,
      "yellow_brick_road": true,
      "yellow_brick_road_count": 1
    },
    {
      "uid": "sn45.110-114",
      "root_name": "Dutiyādisamuddaninnasutta",
      "translated_name": null,
      "acronym": "SN 45.110–114",
      "blurb": null,
      "node_type": "leaf",
      "root_lang_iso": "pli",
      "root_lang_name": "Pāli",
      "child_range": null,
      "yellow_brick_road": true,
      "yellow_brick_road_count": 1
    },
    {
      "uid": "sn45.115",
      "root_name": "Paṭhamapācīnaninnasutta",
      "translated_name": null,
      "acronym": "SN 45.115",
      "blurb": null,
      "node_type": "leaf",
      "root_lang_iso": "pli",
      "root_lang_name": "Pāli",
      "child_range": null,
      "yellow_brick_road": true,
      "yellow_brick_road_count": 2
    },
    {
      "uid": "sn45.116-120",
      "root_name": "Dutiyādipācīnaninnasutta",
      "translated_name": null,
      "acronym": "SN 45.116–120",
      "blurb": null,
      "node_type": "leaf",
      "root_lang_iso": "pli",
      "root_lang_name": "Pāli",
      "child_range": null,
      "yellow_brick_road": true,
      "yellow_brick_road_count": 1
    },
    {
      "uid": "sn45.121",
      "root_name": "Paṭhamasamuddaninnasutta",
      "translated_name": null,
      "acronym": "SN 45.121",
      "blurb": null,
      "node_type": "leaf",
      "root_lang_iso": "pli",
      "root_lang_name": "Pāli",
      "child_range": null,
      "yellow_brick_road": true,
      "yellow_brick_road_count": 1
    },
    {
      "uid": "sn45.122-126",
      "root_name": "Dutiyādisamuddaninnasutta",
      "translated_name": null,
      "acronym": "SN 45.122–126",
      "blurb": null,
      "node_type": "leaf",
      "root_lang_iso": "pli",
      "root_lang_name": "Pāli",
      "child_range": null,
      "yellow_brick_road": true,
      "yellow_brick_road_count": 1
    },
    {
      "uid": "sn45.127",
      "root_name": "Paṭhamapācīnaninnasutta",
      "translated_name": null,
      "acronym": "SN 45.127",
      "blurb": null,
      "node_type": "leaf",
      "root_lang_iso": "pli",
      "root_lang_name": "Pāli",
      "child_range": null,
      "yellow_brick_road": true,
      "yellow_brick_road_count": 2
    },
    {
      "uid": "sn45.128-132",
      "root_name": "Dutiyādipācīnaninnasutta",
      "translated_name": null,
      "acronym": "SN 45.128–132",
      "blurb": null,
      "node_type": "leaf",
      "root_lang_iso": "pli",
      "root_lang_name": "Pāli",
      "child_range": null,
      "yellow_brick_road": true,
      "yellow_brick_road_count": 1
    },
    {
      "uid": "sn45.133",
      "root_name": "Paṭhamasamuddaninnasutta",
      "translated_name": null,
      "acronym": "SN 45.133",
      "blurb": null,
      "node_type": "leaf",
      "root_lang_iso": "pli",
      "root_lang_name": "Pāli",
      "child_range": null,
      "yellow_brick_road": true,
      "yellow_brick_road_count": 1
    },
    {
      "uid": "sn45.134-138",
      "root_name": "Dutiyādisamuddaninnasutta",
      "translated_name": null,
      "acronym": "SN 45.134–138",
      "blurb": null,
      "node_type": "leaf",
      "root_lang_iso": "pli",
      "root_lang_name": "Pāli",
      "child_range": null,
      "yellow_brick_road": true,
      "yellow_brick_road_count": 1
    }
  ]
}